sherlock_ai/__init__.py
sherlock_ai/logging_setup.py
sherlock_ai/analysis/__init__.py
sherlock_ai/analysis/code_analyzer.py
sherlock_ai/analysis/hardcoded_detector.py
sherlock_ai/analysis/smart_check_code.py
sherlock_ai/auto/__init__.py
sherlock_ai/auto/framework_patcher.py
sherlock_ai/auto/function_tracer.py
sherlock_ai/config/__init__.py
sherlock_ai/config/logging.py
sherlock_ai/monitoring/__init__.py
sherlock_ai/monitoring/context_managers.py
sherlock_ai/monitoring/error_insights.py
sherlock_ai/monitoring/global_monitor.py
sherlock_ai/monitoring/monitoring_insights.py
sherlock_ai/monitoring/performance.py
sherlock_ai/monitoring/resource_decorators.py
sherlock_ai/monitoring/resource_monitor.py
sherlock_ai/monitoring/snapshots.py
sherlock_ai/monitoring/utils.py
sherlock_ai/providers/__init__.py
sherlock_ai/providers/azure_openai_provider.py
sherlock_ai/providers/base.py
sherlock_ai/providers/factory.py
sherlock_ai/providers/groq_provider.py
sherlock_ai/storage/__init__.py
sherlock_ai/storage/api_client.py
sherlock_ai/storage/groq_manager.py
sherlock_ai/storage/mongo_manager.py
sherlock_ai/utils/__init__.py
sherlock_ai/utils/request_context.py
sherlock_ai-1.13.0.dist-info/licenses/LICENSE
sherlock_ai-1.13.0.dist-info/METADATA
sherlock_ai-1.13.0.dist-info/WHEEL
sherlock_ai-1.13.0.dist-info/top_level.txt
sherlock_ai-1.13.0.dist-info/RECORD
