Metadata-Version: 2.4
Name: sherlock-ai
Version: 1.13.0
Summary: A Python package for performance monitoring, logging utilities, and code analysis
Author-email: Pranaw Mishra <pranawmishra73@gmail.com>
License: MIT
Project-URL: Homepage, https://github.com/pranawmishra/sherlock-ai.git
Project-URL: Repository, https://github.com/pranawmishra/sherlock-ai.git
Keywords: performance,monitoring,logging,debugging,profiling,analysis
Classifier: Development Status :: 5 - Production/Stable
Classifier: Intended Audience :: Developers
Classifier: License :: OSI Approved :: MIT License
Classifier: Programming Language :: Python :: 3
Classifier: Programming Language :: Python :: 3.8
Classifier: Programming Language :: Python :: 3.9
Classifier: Programming Language :: Python :: 3.10
Classifier: Programming Language :: Python :: 3.11
Classifier: Programming Language :: Python :: 3.12
Classifier: Topic :: Software Development :: Libraries :: Python Modules
Classifier: Topic :: System :: Monitoring
Requires-Python: >=3.8
License-File: LICENSE
Requires-Dist: astor>=0.8.1
Requires-Dist: fastapi>=0.116.1
Requires-Dist: groq>=0.30.0
Requires-Dist: openai>=2.2.0
Requires-Dist: psutil>=5.8.0
Requires-Dist: pymongo>=4.10.1
Requires-Dist: python-dotenv>=1.0.1
Requires-Dist: requests>=2.32.4
Requires-Dist: uvicorn>=0.33.0
Dynamic: license-file
